textgraphs/__init__.py
textgraphs/defaults.py
textgraphs/doc.py
textgraphs/elem.py
textgraphs/gor.py
textgraphs/graph.py
textgraphs/kg.py
textgraphs/ner.py
textgraphs/pipe.py
textgraphs/rel.py
textgraphs/util.py
textgraphs/version.py
textgraphs/vis.py
textgraphs-0.5.0.dist-info/LICENSE
textgraphs-0.5.0.dist-info/METADATA
textgraphs-0.5.0.dist-info/WHEEL
textgraphs-0.5.0.dist-info/top_level.txt
textgraphs-0.5.0.dist-info/RECORD
