Metadata-Version: 2.1
Name: textgraphs
Version: 0.5.0
Summary: TextGraphs + LLMs + graph ML for entity extraction, linking, ranking, and constructing a lemma graph
Author-email: "derwen.ai" <info@derwen.ai>
License: MIT License
Project-URL: home, https://huggingface.co/spaces/DerwenAI/textgraphs
Project-URL: docs, https://derwen.ai/docs/txg/
Project-URL: code, https://github.com/DerwenAI/textgraphs
Project-URL: PyPi, https://pypi.org/project/textgraphs/
Project-URL: DOI, https://zenodo.org/doi/10.5281/zenodo.10431783
Classifier: Development Status :: 3 - Alpha
Classifier: License :: OSI Approved :: MIT License
Classifier: Natural Language :: English
Classifier: Intended Audience :: Developers
Classifier: Intended Audience :: Education
Classifier: Intended Audience :: Information Technology
Classifier: Intended Audience :: Science/Research
Classifier: Topic :: Scientific/Engineering :: Artificial Intelligence
Classifier: Topic :: Scientific/Engineering :: Human Machine Interfaces
Classifier: Topic :: Scientific/Engineering :: Information Analysis
Classifier: Topic :: Scientific/Engineering :: Visualization
Classifier: Topic :: Software Development :: Libraries :: Python Modules
Classifier: Topic :: Text Processing :: Indexing
Classifier: Topic :: Text Processing :: Linguistic
Classifier: Operating System :: OS Independent
Classifier: Programming Language :: Python
Classifier: Programming Language :: Python :: 3.10
Requires-Python: >=3.10
License-File: LICENSE
Requires-Dist: beautifulsoup4 >=4.12
Requires-Dist: GitPython >=3.1
Requires-Dist: icecream >=2.1
Requires-Dist: markdown2 >=2.4
Requires-Dist: matplotlib >=3.8
Requires-Dist: networkx >=3.2
Requires-Dist: open-nre >=0.1.1
Requires-Dist: pulp >=2.7
Requires-Dist: pyinstrument >=4.6
Requires-Dist: pyvis >=0.3
Requires-Dist: qwikidata >=0.4
Requires-Dist: rdflib >=7.0
Requires-Dist: spacy >=3.7
Requires-Dist: spacy-dbpedia-spotlight >=0.2.6
Requires-Dist: span-marker >=1.5
Requires-Dist: transformers >=4.35
Requires-Dist: wordcloud >=1.9
Provides-Extra: demo
Requires-Dist: ipywidgets >=8.1 ; extra == 'demo'
Requires-Dist: jupyterlab-execute-time >=3.1 ; extra == 'demo'
Requires-Dist: jupyterlab >=4.0 ; extra == 'demo'
Requires-Dist: kuzu >=0.1 ; extra == 'demo'
Requires-Dist: sense2vec >=2.0 ; extra == 'demo'
Requires-Dist: spacy-entity-linker >=1.0 ; extra == 'demo'
Requires-Dist: streamlit <1.29 ; extra == 'demo'
Requires-Dist: watermark >=2.4 ; extra == 'demo'
Provides-Extra: dev
Requires-Dist: build >=1.0 ; extra == 'dev'
Requires-Dist: Flask >=3.0 ; extra == 'dev'
Requires-Dist: mkdocs-git-revision-date-plugin >=0.3 ; extra == 'dev'
Requires-Dist: mkdocs-material >=9.5 ; extra == 'dev'
Requires-Dist: mknotebooks >=0.8 ; extra == 'dev'
Requires-Dist: pre-commit >=3.5 ; extra == 'dev'
Requires-Dist: selenium >=4.16 ; extra == 'dev'
Requires-Dist: twine >=4.0 ; extra == 'dev'
Provides-Extra: test
Requires-Dist: pytest >=7.4 ; extra == 'test'
Requires-Dist: deepdiff >=6.7 ; extra == 'test'
